{
  "project_info": {
    "project_number": "541147176187",
    "project_id": "flutter-project-2a8a6",
    "storage_bucket": "flutter-project-2a8a6.appspot.com"
  },
  "client": [
    {
      "client_info": {
        "mobilesdk_app_id": "1:541147176187:android:e3cc3be0d333f1aba5a45e",
        "android_client_info": {
          "package_name": "com.example.flutter_project"
        }
      },
      "oauth_client": [
        {
          "client_id": "541147176187-dqpm6rqj74a3lp7flddnhc7ira47vevv.apps.googleusercontent.com",
          "client_type": 3
        }
      ],
      "api_key": [
        {
          "current_key": "AIzaSyAu3G4kfc7Ag29Qs1pQW4zISJbPyvxFxaY"
        }
      ],
      "services": {
        "appinvite_service": {
          "other_platform_oauth_client": [
            {
              "client_id": "541147176187-dqpm6rqj74a3lp7flddnhc7ira47vevv.apps.googleusercontent.com",
              "client_type": 3
            },
            {
              "client_id": "541147176187-j8pd48qmdbrs8fvj4petostecb0c8vi5.apps.googleusercontent.com",
              "client_type": 2,
              "ios_info": {
                "bundle_id": "com.example.flutterProject"
              }
            }
          ]
        }
      }
    }
  ],
  "configuration_version": "1"
}